xit/__meta__.py
xit/tools.py
xit-0.0.2.dist-info/LICENSE
xit-0.0.2.dist-info/WHEEL
xit-0.0.2.dist-info/METADATA
xit-0.0.2.dist-info/RECORD
