Metadata-Version: 2.1
Name: xit
Version: 0.0.2
Summary: A namespace for a group of related projects.
Home-page: https://github.com/med-merchise/xit
License: GPL-3.0-or-later
Author: Medardo Antonio Rodriguez
Requires-Python: >=3.10,<4.0
Classifier: Development Status :: 1 - Planning
Classifier: Intended Audience :: Developers
Classifier: License :: OSI Approved :: GNU General Public License v3 or later (GPLv3+)
Classifier: Programming Language :: Python
Classifier: Programming Language :: Python :: 3
Classifier: Programming Language :: Python :: 3.10
Classifier: Programming Language :: Python :: 3.11
Classifier: Topic :: Documentation
Classifier: Topic :: Software Development
Project-URL: Repository, https://github.com/med-merchise/xit
